univllm/__init__.py
univllm/client.py
univllm/exceptions.py
univllm/models.py
univllm/supported_models.py
univllm/providers/__init__.py
univllm/providers/anthropic_provider.py
univllm/providers/base.py
univllm/providers/deepseek_provider.py
univllm/providers/gemini_provider.py
univllm/providers/mistral_provider.py
univllm/providers/openai_provider.py
univllm-0.1.12.dist-info/METADATA
univllm-0.1.12.dist-info/WHEEL
univllm-0.1.12.dist-info/top_level.txt
univllm-0.1.12.dist-info/RECORD
