Metadata-Version: 2.4
Name: univllm
Version: 0.1.12
Summary: Universal interface for different LLM providers
Author-email: nihilok <nihilok@ush.name>
License: MIT
Project-URL: Homepage, https://github.com/nihilok/univllm
Project-URL: Repository, https://github.com/nihilok/univllm
Classifier: Development Status :: 3 - Alpha
Classifier: Intended Audience :: Developers
Classifier: License :: OSI Approved :: MIT License
Classifier: Programming Language :: Python :: 3
Classifier: Programming Language :: Python :: 3.9
Classifier: Programming Language :: Python :: 3.10
Classifier: Programming Language :: Python :: 3.11
Classifier: Programming Language :: Python :: 3.12
Requires-Python: >=3.9
Requires-Dist: openai==1.108.1
Requires-Dist: anthropic==0.68.0
Requires-Dist: mistralai==1.9.10
Requires-Dist: httpx==0.28.1
Requires-Dist: pydantic==2.11.9
Requires-Dist: python-dotenv==1.1.1
Requires-Dist: pytest==8.4.2
Requires-Dist: google-genai==1.61.0
